{
  "id": "4722d760-f9db-46de-bc5d-6619a8878f19",
  "name": "Hel",
  "description": "",
  "preview_url": "https://preview.templr.io/v/f2fyl194",
  "image_preview": "https://i.ibb.co/5WmN4w9n/1773647883205-1773485971498.jpg",
  "banner_url": "https://i.ibb.co/5WmN4w9n/1773647883205-1773485971498.jpg",
  "gallery_images": [
    "https://i.ibb.co/5WmN4w9n/1773647883205-1773485971498.jpg"
  ],
  "file_url": "",
  "tags": [],
  "creator": "Lapis",
  "creator_email": "templrsaas@gmail.com",
  "created_at": "2026-03-16T07:58:19.244Z",
  "category": "Landing Page",
  "price": "Free",
  "stats": {
    "likes": 0,
    "views": 0
  }
}